snowflake/ingest/__init__.py
snowflake/ingest/error.py
snowflake/ingest/errorcode.py
snowflake/ingest/simple_ingest_manager.py
snowflake/ingest/version.py
snowflake/ingest/utils/__init__.py
snowflake/ingest/utils/network.py
snowflake/ingest/utils/tokentools.py
snowflake/ingest/utils/uris.py
snowflake_ingest_pyjwt_2-2.0.0a1.dist-info/LICENSE
snowflake_ingest_pyjwt_2-2.0.0a1.dist-info/METADATA
snowflake_ingest_pyjwt_2-2.0.0a1.dist-info/WHEEL
snowflake_ingest_pyjwt_2-2.0.0a1.dist-info/top_level.txt
snowflake_ingest_pyjwt_2-2.0.0a1.dist-info/RECORD
