Metadata-Version: 2.1
Name: snowflake-ingest-pyjwt-2
Version: 2.0.0a1
Summary: Unofficial & (hopefully) temporary fork of SnowflakeDB File Ingest SDK to allow use 
Home-page: https://www.snowflake.net
Author: Joshua Skrzypek
Author-email: jskrzypek@gmail.com
License: Apache
Keywords: snowflake ingest sdk copy loading
Classifier: Development Status :: 2 - Pre-Alpha
Classifier: Intended Audience :: Developers
Classifier: License :: OSI Approved :: Apache Software License
Classifier: Topic :: Database
License-File: LICENSE
Requires-Dist: pyjwt
Requires-Dist: snowflake-connector-python
Requires-Dist: furl
Requires-Dist: cryptography
Requires-Dist: requests
